todo_table/__init__.py
todo_table/cli.py
todo_table/database.py
todo_table/py.typed
todo_table/todo.py
todo_table-0.1.0.dist-info/METADATA
todo_table-0.1.0.dist-info/WHEEL
todo_table-0.1.0.dist-info/entry_points.txt
todo_table-0.1.0.dist-info/RECORD
